{
  "Ads": [
    {
      "select_main_ads": "null",
      "select_backup_ads":"APPLOVIN-M",
      "main_ads_banner": "",
      "main_ads_intertitial":"",
      "main_ads_natives":"",
      "backup_ads_natives":"f26eaf0eb968bfd4",
      "backup_ads_banner":"",
      "backup_ads_intertitial":"10ec28a9ceed6e41",
      "open_ads_admob":"",
      "open_ads_alien":"",
      "open_ads_max" :"",
      "open_ads_wortise":"",
      "interval_intertitial": 1,
      "initialize_sdk":"107355779",
      "initialize_sdk_backup_ads":"",
      "high_paying_keyword_1": "",
      "high_paying_keyword_2": "",
      "high_paying_keyword_3": "",
      "high_paying_keyword_4": "",
      "high_paying_keyword_5": "",
      "status_app": "0",
      "link_redirect": "https://"
    }
  ],
  "Maps": [
    {
      "name_map": "MOD MAP BLUSUKAN DI WONOSOBO",
      "view_map": "https://i.ytimg.com/vi/SaIvVtFKTvk/maxresdefault.jpg",
      "map_url": "https://archive.org/download/mod-map-blusukan-di-wonosobo/MOD%20MAP%20BLUSUKAN%20DI%20WONOSOBO.bussidmod"
    },
    {
      "name_map": "full jalur khusus ofroad",
      "view_map": "https://i.ytimg.com/vi/ZEf5Js83zqY/maxresdefault.jpg",
      "map_url": "https://archive.org/download/mod-map-blusukan-di-wonosobo/full%20jalur%20khusus%20ofroad.bussidmod"
    },
    {
      "name_map": "Map Kelok Jalan-Rusak",
      "view_map": "https://media.thelastsurvivors.org/2022/11/Mod-Map-Kelok-44-Jalan-Rusak.webp",
      "map_url": "https://archive.org/download/mod-map-blusukan-di-wonosobo/mod%20map%20blusukan.bussidmod"
    },
    {
      "name_map": "bukit bintang",
      "view_map": "https://i.ytimg.com/vi/H8ZAQUU_6sY/maxresdefault.jpg",
      "map_url": "https://archive.org/download/mod-map-blusukan-di-wonosobo/bukit%20bintang%20amdroid93.bussidmod"
    }
  ],
  "Mods": [
    {
      "title": "Karnataka_gramantara",
      "image": "https://i.ytimg.com/vi/XCG1ES1hvpA/hqdefault.jpg",
      "category": "Bus",
      "link_mods": "https://archive.org/download/karnataka_SRTC_bus_mod/Karnataka_gramantara_sarige_Cb_project.bussidmod",
      "name_livery": "null",
      "link_livery": "null",
      "name_livery2": "null",
      "link_livery2": "null"
    },
    {
      "title": "karnataka_SRTC",
      "image": "https://i.ytimg.com/vi/XjX7qROsMyU/maxresdefault.jpg",
      "category": "Bus",
      "link_mods": "https://archive.org/download/karnataka_SRTC_bus_mod/karnataka_SRTC_bus_mod.bussidmod",
      "name_livery": "null",
      "link_livery": "null",
      "name_livery2": "null",
      "link_livery2": "null"
    },
    {
      "title": "karnataka_kbsx",
      "image": "https://i.ytimg.com/vi/YlwsxNSJpwo/maxresdefault.jpg",
      "category": "Bus",
      "link_mods": "https://archive.org/download/karnataka_SRTC_bus_mod/karnataka_rtc_by_team_kbs.bussidvehicle",
      "name_livery": "null",
      "link_livery": "null",
      "name_livery2": "null",
      "link_livery2": "null"
    },
    {
      "title": "NEW_PRAKASH_GRAND_BMR",
      "image": "https://play-lh.googleusercontent.com/-P2jD41hswuUcPMgnGFhx2tcaTDYOJksLLDv0_Fz8nWPjbS-YSo_SJ-o0SrbqC1rGriu",
      "category": "Truk",
      "link_mods": "https://archive.org/download/tk-zed-one-bc-v-1/NEW_PRAKASH_GRAND_BMR_.bussidmod",
      "name_livery": "null",
      "link_livery": "null",
      "name_livery2": "null",
      "link_livery2": "null"
    },
    {
      "title": "ap-GRTx",
      "image": "https://i.ytimg.com/vi/gXwCuSyKoCM/mqdefault.jpg",
      "category": "Truk",
      "link_mods": "https://archive.org/download/tk-zed-one-bc-v-1/ap-tsrtc_by_CjProject.bussidmod",
      "name_livery": "null",
      "link_livery": "null",
      "name_livery2": "null",
      "link_livery2": "null"
    },
    {
      "title": "MTC_ROOD",
      "image": "https://play-lh.googleusercontent.com/xmPf7Wt8suVSym_LI9KB8vsFiSS9ly2WPxTFVkujT__xCiYR5VHz4EFAZPWtQyW-AQ=w750-h750",
      "category": "Mobil",
      "link_mods": "hhttps://archive.org/download/tk-zed-one-bc-v-1/TamilNadu%20MTC%20Red%20Bus.bussidmod",
      "name_livery": "null",
      "link_livery": "null",
      "name_livery2": "null",
      "link_livery2": "null"
    },
    {
      "title": "KRP_OKT",
      "image": "https://play-lh.googleusercontent.com/dUpKEJXgzOAPL0bu-6pUAbKODb-gdmNk2evLrcKT_pLrP9xHCYyLwbkPmycsXbyV7zqR",
      "category": "Mobil",
      "link_mods": "https://archive.org/download/tk-zed-one-bc-v-1/TK_ZED_ONE_BC_V1_.bussidmod",
      "name_livery": "null",
      "link_livery": "null",
      "name_livery2": "null",
      "link_livery2": "null"
    },
    {
      "title": "Maruthi OTJ",
      "image": "https://i.ytimg.com/vi/1iuMo3Ankwo/hqdefault.jpg",
      "category": "Mobil",
      "link_mods": "https://archive.org/download/tk-zed-one-bc-v-1/Maruthi_v2_AKBDA.bussidmod",
      "name_livery": "null",
      "link_livery": "null",
      "name_livery2": "null",
      "link_livery2": "null"
    },
    {
      "title": "LUXURA",
      "image": "https://i.ytimg.com/vi/_gpExM75zZo/hq720.jpg?sqp=-oaymwEhCK4FEIIDSFryq4qpAxMIARUAAAAAGAElAADIQj0AgKJD&rs=AOn4CLCda-HMBdeXECjetgM7y02Oo9qLWQ",
      "category": "Mobil",
      "link_mods": "https://archive.org/download/tk-zed-one-bc-v-1/KONDODY_LUXURA_SDLX_VIKING_12M_BS4_V1.bussidmod",
      "name_livery": "null",
      "link_livery": "null",
      "name_livery2": "null",
      "link_livery2": "null"
    },
    {
      "title": "SD DOP",
      "image": "https://image.winudf.com/v2/image1/Y29tLmthcm5hdGFrYS50cmFmZmljLm1vZF9zY3JlZW5fMF8xNjc4ODQ4NTM1XzAwOQ/screen-0.webp?fakeurl=1&type=.webp",
      "category": "Mobil",
      "link_mods": "https://archive.org/download/tk-zed-one-bc-v-1/JB3%2B%20SDD%20Versi%20Dop%20-%20Javastech.com.bussidmod",
      "name_livery": "null",
      "link_livery": "null",
      "name_livery2": "null",
      "link_livery2": "null"
    }
  ],
  "Audio": [
    {
      "title_mp3": "Pujian Hasbunallah Wa Ni'mal Wakil",
      "name": "Santri Njoso",
      "url_mp3": "https://aliendro.id/uploads/demo/premiumbussid/hasbunallah.mp3"
    },
    {
      "title_mp3": "Al'Itiraf - Sebuah pengakuan",
      "name": "Alfina Nindiyani",
      "url_mp3": "https://aliendro.id/uploads/demo/premiumbussid/altiraf.mp3"
    },
    {
      "title_mp3": "Do'a Rajab",
      "name": "Alfina Nindiyani",
      "url_mp3": "https://aliendro.id/uploads/demo/premiumbussid/rajab.mp3"
    },
    {
      "title_mp3": "Allahul kaafi",
      "name": "Bebiraira Channel",
      "url_mp3": "https://aliendro.id/uploads/demo/premiumbussid/Allahul kaafi.mp3"
    },
    {
      "title_mp3": "Rindu Madinah Cover By Umar Razeeq ft Mujib",
      "name": "Shatibiyyah Studio",
      "url_mp3": "https://aliendro.id/uploads/demo/premiumbussid/rindu.mp3"
    },
    {
      "title_mp3": "Train Horn",
      "name": "Zedge",
      "url_mp3": "https://aliendro.id/uploads/demo/premiumbussid/train_horn.mp3"
    },
    {
      "title_mp3": "Dixie Horn",
      "name": "Zedge",
      "url_mp3": "https://aliendro.id/uploads/demo/premiumbussid/dixie_horn.mp3"
    },
    {
      "title_mp3": "Clown Horn",
      "name": "Zedge",
      "url_mp3": "https://aliendro.id/uploads/demo/premiumbussid/clown_horn.mp3"
    }
  ],
  "Radio": [
    {
      "title_radio": "Rodja 756 AM",
      "url_radio": "https://radioislamindonesia.com/rodja.mp3?_=2"
    },
    {
      "title_radio": "Suara Al-Iman 846 AM",
      "url_radio": "https://radioislamindonesia.com/aliman.mp3"
    },
    {
      "title_radio": "Tarbiyah Sunnah 1476 AM",
      "url_radio": "https://radioislamindonesia.com/tarbiyah.mp3"
    },
    {
      "title_radio": "kalam FM 100.6 Mhz",
      "url_radio": "https://radioislamindonesia.com/idzaatulkhair.mp3"
    },
    {
      "title_radio": "Mutiara Qu'an 1170 am",
      "url_radio": "https://radioislamindonesia.com/mutiaraquran.mp3"
    },
    {
      "title_radio": "Hidayah 103,4 FM",
      "url_radio": "https://radioislamindonesia.com/radiohidayah.mp3"
    },
    {
      "title_radio": "Madinah FM 107,7 Mhz",
      "url_radio": "https://radioislamindonesia.com/radiomadinah.mp3"
    },
    {
      "title_radio": "Muadz 94.3 FM",
      "url_radio": "https://radioislamindonesia.com/radiomuadz.mp3"
    },
    {
      "title_radio": "Shahabat Muslim 107.7 FM",
      "url_radio": "https://radioislamindonesia.com/shahabatmuslim.mp3"
    },
    {
      "title_radio": "SKN Al-Bayaan 95 FM",
      "url_radio": "https://server-s5.xajist.com/sslstream/8526/"
    }
  ]
}
